accqsure/__init__.py
accqsure/__main__.py
accqsure/accqsure.py
accqsure/auth.py
accqsure/document_types.py
accqsure/documents.py
accqsure/enums.py
accqsure/exceptions.py
accqsure/inspections.py
accqsure/manifests.py
accqsure/text.py
accqsure/util.py
accqsure/charts/__init__.py
accqsure/charts/charts.py
accqsure/charts/elements.py
accqsure/charts/sections.py
accqsure/charts/waypoints.py
accqsure/cli/__init__.py
accqsure/cli/chart.py
accqsure/cli/document.py
accqsure/cli/document_type.py
accqsure/cli/inspection.py
accqsure/cli/manifest.py
accqsure/cli/manifest_check.py
accqsure/cli/plot.py
accqsure/cli/text.py
accqsure/plots/__init__.py
accqsure/plots/elements.py
accqsure/plots/markers.py
accqsure/plots/plots.py
accqsure/plots/sections.py
accqsure/plots/waypoints.py
tests/charts/__init__.py
tests/charts/test_charts.py
tests/charts/test_elements.py
tests/charts/test_sections.py
tests/charts/test_waypoints.py
tests/plots/__init__.py
tests/plots/test_elements.py
tests/plots/test_markers.py
tests/plots/test_plots.py
tests/plots/test_sections.py
tests/plots/test_waypoints.py
accqsure-0.3.1.dist-info/LICENSE
accqsure-0.3.1.dist-info/METADATA
accqsure-0.3.1.dist-info/WHEEL
accqsure-0.3.1.dist-info/entry_points.txt
accqsure-0.3.1.dist-info/top_level.txt
accqsure-0.3.1.dist-info/RECORD
