Metadata-Version: 2.1
Name: accqsure
Version: 0.3.1
Summary: AccQsure client SDK and command line utilities
Home-page: https://github.com/AccQsure/python-sdk
Author: AccQsure, Inc.
Author-email: support@accqsure.ai
License: MIT
Classifier: License :: OSI Approved :: MIT License
Classifier: Programming Language :: Python :: 3
Classifier: Programming Language :: Python :: 3.10
Requires-Python: >=3.10
License-File: LICENSE
Requires-Dist: aiohttp
Requires-Dist: aiofiles
Requires-Dist: Click>8
Requires-Dist: cryptography
